distance_transforms/__init__.py
distance_transforms/julia_import.py
distance_transforms/transform.py
distance_transforms/transform_cuda.py
distance_transforms-0.1.1.dist-info/METADATA
distance_transforms-0.1.1.dist-info/WHEEL
distance_transforms-0.1.1.dist-info/top_level.txt
distance_transforms-0.1.1.dist-info/RECORD
