Metadata-Version: 2.2
Name: distance_transforms
Version: 0.1.1
Summary: Python bindings for the Julia DistanceTransforms.jl package
Requires-Python: >=3.11
Requires-Dist: juliacall>=0.9.24
Requires-Dist: numpy>=2.2.3
Requires-Dist: torch>=2.6.0
Provides-Extra: dev
Requires-Dist: pytest>=8.3.5; extra == "dev"
